kafkian/__init__.py
kafkian/consumer.py
kafkian/consumer_schema_mapper.py
kafkian/exceptions.py
kafkian/message.py
kafkian/producer.py
kafkian/metrics/__init__.py
kafkian/metrics/consts.py
kafkian/serde/__init__.py
kafkian/serde/avroserdebase.py
kafkian/serde/deserialization.py
kafkian/serde/serialization.py
kafkian-0.15.1.dist-info/licenses/LICENSE
kafkian-0.15.1.dist-info/METADATA
kafkian-0.15.1.dist-info/WHEEL
kafkian-0.15.1.dist-info/top_level.txt
kafkian-0.15.1.dist-info/RECORD
