Metadata-Version: 2.4
Name: kafkian
Version: 0.15.1
Summary: Opinionated Kafka Python client on top of Confluent python library
Home-page: https://github.com/saabeilin/kafkian
Author: Sergei Beilin
Author-email: saabeilin@gmail.com
License: Apache 2.0
Keywords: kafka
Classifier: Development Status :: 3 - Alpha
Classifier: License :: OSI Approved :: Apache Software License
Classifier: Programming Language :: Python :: 3.11
Classifier: Programming Language :: Python :: 3.12
Classifier: Programming Language :: Python :: 3.13
License-File: LICENSE
Requires-Dist: confluent-kafka>=2.3.0
Requires-Dist: fastavro>=1.9.7
Requires-Dist: avro>=1.12.0
Dynamic: author
Dynamic: author-email
Dynamic: classifier
Dynamic: description
Dynamic: description-content-type
Dynamic: home-page
Dynamic: keywords
Dynamic: license
Dynamic: license-file
Dynamic: requires-dist
Dynamic: summary
